{"services":[{"i":"kcbus:01001","d":[1,1,1,1,1,0,0],"s":"20260320","e":"20270331"},{"i":"kcbus:01001_A","d":[1,1,1,1,1,0,0],"s":"20260320","e":"20270331"},{"i":"kcbus:01001_GYB","d":[1,1,1,1,1,0,0],"s":"20260320","e":"20270331"},{"i":"kcbus:01002_RIT","d":[1,1,1,1,1,0,0],"s":"20260320","e":"20270331"},{"i":"kcbus:01003_KSU","d":[1,1,1,1,1,0,0],"s":"20260320","e":"20270331"},{"i":"kcbus:01004_BUK","d":[1,1,1,1,1,0,0],"s":"20260320","e":"20270331"},{"i":"kcbus:01005_MSN","d":[1,1,1,1,1,0,0],"s":"20260320","e":"20270331"},{"i":"kcbus:02001","d":[0,0,0,0,0,0,1],"s":"20260320","e":"20270331"},{"i":"kcbus:02001_A","d":[0,0,0,0,0,0,1],"s":"20260320","e":"20270331"},{"i":"kcbus:02001_GYB","d":[0,0,0,0,0,0,1],"s":"20260320","e":"20270331"},{"i":"kcbus:03001","d":[0,0,0,0,0,1,0],"s":"20260320","e":"20270331"},{"i":"kcbus:03001_A","d":[0,0,0,0,0,1,0],"s":"20260320","e":"20270331"},{"i":"kcbus:03001_GYB","d":[0,0,0,0,0,1,0],"s":"20260320","e":"20270331"}],"exceptions":[{"i":"kcbus:01001","d":"20260320","t":2},{"i":"kcbus:01001","d":"20260429","t":2},{"i":"kcbus:01001","d":"20260504","t":2},{"i":"kcbus:01001","d":"20260505","t":2},{"i":"kcbus:01001","d":"20260506","t":2},{"i":"kcbus:01001","d":"20260720","t":2},{"i":"kcbus:01001","d":"20260811","t":2},{"i":"kcbus:01001","d":"20260814","t":2},{"i":"kcbus:01001","d":"20260921","t":2},{"i":"kcbus:01001","d":"20260922","t":2},{"i":"kcbus:01001","d":"20260923","t":2},{"i":"kcbus:01001","d":"20261012","t":2},{"i":"kcbus:01001","d":"20261103","t":2},{"i":"kcbus:01001","d":"20261123","t":2},{"i":"kcbus:01001","d":"20261229","t":2},{"i":"kcbus:01001","d":"20261230","t":2},{"i":"kcbus:01001","d":"20261231","t":2},{"i":"kcbus:01001","d":"20270101","t":2},{"i":"kcbus:01001","d":"20270111","t":2},{"i":"kcbus:01001","d":"20270211","t":2},{"i":"kcbus:01001","d":"20270223","t":2},{"i":"kcbus:01001","d":"20270322","t":2},{"i":"kcbus:01001_A","d":"20260320","t":2},{"i":"kcbus:01001_A","d":"20260323","t":2},{"i":"kcbus:01001_A","d":"20260324","t":2},{"i":"kcbus:01001_A","d":"20260325","t":2},{"i":"kcbus:01001_A","d":"20260326","t":2},{"i":"kcbus:01001_A","d":"20260327","t":2},{"i":"kcbus:01001_A","d":"20260330","t":2},{"i":"kcbus:01001_A","d":"20260331","t":2},{"i":"kcbus:01001_A","d":"20260401","t":2},{"i":"kcbus:01001_A","d":"20260402","t":2},{"i":"kcbus:01001_A","d":"20260403","t":2},{"i":"kcbus:01001_A","d":"20260429","t":2},{"i":"kcbus:01001_A","d":"20260504","t":2},{"i":"kcbus:01001_A","d":"20260505","t":2},{"i":"kcbus:01001_A","d":"20260506","t":2},{"i":"kcbus:01001_C","d":"20260323","t":1},{"i":"kcbus:01001_C","d":"20260324","t":1},{"i":"kcbus:01001_C","d":"20260325","t":1},{"i":"kcbus:01001_C","d":"20260326","t":1},{"i":"kcbus:01001_C","d":"20260327","t":1},{"i":"kcbus:01001_C","d":"20260330","t":1},{"i":"kcbus:01001_C","d":"20260331","t":1},{"i":"kcbus:01001_C","d":"20260401","t":1},{"i":"kcbus:01001_C","d":"20260402","t":1},{"i":"kcbus:01001_C","d":"20260403","t":1},{"i":"kcbus:01001_GYB","d":"20260320","t":2},{"i":"kcbus:01001_GYB","d":"20260429","t":2},{"i":"kcbus:01001_GYB","d":"20260504","t":2},{"i":"kcbus:01001_GYB","d":"20260505","t":2},{"i":"kcbus:01001_GYB","d":"20260506","t":2},{"i":"kcbus:01001_GYB","d":"20260710","t":2},{"i":"kcbus:01001_GYB","d":"20260715","t":2},{"i":"kcbus:01001_GYB","d":"20260716","t":2},{"i":"kcbus:01001_GYB","d":"20260717","t":2},{"i":"kcbus:01001_GYB","d":"20260720","t":2},{"i":"kcbus:01001_GYB","d":"20260724","t":2},{"i":"kcbus:01001_GYB","d":"20260728","t":2},{"i":"kcbus:01001_GYB","d":"20260811","t":2},{"i":"kcbus:01001_GYB","d":"20260814","t":2},{"i":"kcbus:01001_GYB","d":"20260921","t":2},{"i":"kcbus:01001_GYB","d":"20260922","t":2},{"i":"kcbus:01001_GYB","d":"20260923","t":2},{"i":"kcbus:01001_GYB","d":"20261012","t":2},{"i":"kcbus:01001_GYB","d":"20261103","t":2},{"i":"kcbus:01001_GYB","d":"20261123","t":2},{"i":"kcbus:01001_GYB","d":"20261229","t":2},{"i":"kcbus:01001_GYB","d":"20261230","t":2},{"i":"kcbus:01001_GYB","d":"20261231","t":2},{"i":"kcbus:01001_GYB","d":"20270101","t":2},{"i":"kcbus:01001_GYB","d":"20270111","t":2},{"i":"kcbus:01001_GYB","d":"20270211","t":2},{"i":"kcbus:01001_GYB","d":"20270223","t":2},{"i":"kcbus:01001_GYB","d":"20270322","t":2},{"i":"kcbus:01002_RIT","d":"20260320","t":2},{"i":"kcbus:01002_RIT","d":"20260323","t":2},{"i":"kcbus:01002_RIT","d":"20260324","t":2},{"i":"kcbus:01002_RIT","d":"20260325","t":2},{"i":"kcbus:01002_RIT","d":"20260326","t":2},{"i":"kcbus:01002_RIT","d":"20260327","t":2},{"i":"kcbus:01002_RIT","d":"20260330","t":2},{"i":"kcbus:01002_RIT","d":"20260331","t":2},{"i":"kcbus:01002_RIT","d":"20260429","t":2},{"i":"kcbus:01002_RIT","d":"20260504","t":2},{"i":"kcbus:01002_RIT","d":"20260505","t":2},{"i":"kcbus:01002_RIT","d":"20260506","t":2},{"i":"kcbus:01002_RIT","d":"20260720","t":2},{"i":"kcbus:01002_RIT","d":"20260727","t":2},{"i":"kcbus:01002_RIT","d":"20260728","t":2},{"i":"kcbus:01002_RIT","d":"20260729","t":2},{"i":"kcbus:01002_RIT","d":"20260730","t":2},{"i":"kcbus:01002_RIT","d":"20260731","t":2},{"i":"kcbus:01002_RIT","d":"20260803","t":2},{"i":"kcbus:01002_RIT","d":"20260804","t":2},{"i":"kcbus:01002_RIT","d":"20260805","t":2},{"i":"kcbus:01002_RIT","d":"20260806","t":2},{"i":"kcbus:01002_RIT","d":"20260807","t":2},{"i":"kcbus:01002_RIT","d":"20260810","t":2},{"i":"kcbus:01002_RIT","d":"20260811","t":2},{"i":"kcbus:01002_RIT","d":"20260812","t":2},{"i":"kcbus:01002_RIT","d":"20260813","t":2},{"i":"kcbus:01002_RIT","d":"20260814","t":2},{"i":"kcbus:01002_RIT","d":"20260817","t":2},{"i":"kcbus:01002_RIT","d":"20260818","t":2},{"i":"kcbus:01002_RIT","d":"20260819","t":2},{"i":"kcbus:01002_RIT","d":"20260820","t":2},{"i":"kcbus:01002_RIT","d":"20260821","t":2},{"i":"kcbus:01002_RIT","d":"20260824","t":2},{"i":"kcbus:01002_RIT","d":"20260825","t":2},{"i":"kcbus:01002_RIT","d":"20260826","t":2},{"i":"kcbus:01002_RIT","d":"20260827","t":2},{"i":"kcbus:01002_RIT","d":"20260828","t":2},{"i":"kcbus:01002_RIT","d":"20260831","t":2},{"i":"kcbus:01002_RIT","d":"20260901","t":2},{"i":"kcbus:01002_RIT","d":"20260902","t":2},{"i":"kcbus:01002_RIT","d":"20260903","t":2},{"i":"kcbus:01002_RIT","d":"20260904","t":2},{"i":"kcbus:01002_RIT","d":"20260907","t":2},{"i":"kcbus:01002_RIT","d":"20260908","t":2},{"i":"kcbus:01002_RIT","d":"20260909","t":2},{"i":"kcbus:01002_RIT","d":"20260910","t":2},{"i":"kcbus:01002_RIT","d":"20260911","t":2},{"i":"kcbus:01002_RIT","d":"20260914","t":2},{"i":"kcbus:01002_RIT","d":"20260915","t":2},{"i":"kcbus:01002_RIT","d":"20260916","t":2},{"i":"kcbus:01002_RIT","d":"20260917","t":2},{"i":"kcbus:01002_RIT","d":"20260918","t":2},{"i":"kcbus:01002_RIT","d":"20260921","t":2},{"i":"kcbus:01002_RIT","d":"20260922","t":2},{"i":"kcbus:01002_RIT","d":"20260923","t":2},{"i":"kcbus:01002_RIT","d":"20260924","t":2},{"i":"kcbus:01002_RIT","d":"20260925","t":2},{"i":"kcbus:01002_RIT","d":"20261012","t":2},{"i":"kcbus:01002_RIT","d":"20261103","t":2},{"i":"kcbus:01002_RIT","d":"20261123","t":2},{"i":"kcbus:01002_RIT","d":"20261228","t":2},{"i":"kcbus:01002_RIT","d":"20261229","t":2},{"i":"kcbus:01002_RIT","d":"20261230","t":2},{"i":"kcbus:01002_RIT","d":"20261231","t":2},{"i":"kcbus:01002_RIT","d":"20270101","t":2},{"i":"kcbus:01002_RIT","d":"20270104","t":2},{"i":"kcbus:01002_RIT","d":"20270105","t":2},{"i":"kcbus:01002_RIT","d":"20270111","t":2},{"i":"kcbus:01002_RIT","d":"20270125","t":2},{"i":"kcbus:01002_RIT","d":"20270126","t":2},{"i":"kcbus:01002_RIT","d":"20270127","t":2},{"i":"kcbus:01002_RIT","d":"20270128","t":2},{"i":"kcbus:01002_RIT","d":"20270129","t":2},{"i":"kcbus:01002_RIT","d":"20270201","t":2},{"i":"kcbus:01002_RIT","d":"20270202","t":2},{"i":"kcbus:01002_RIT","d":"20270203","t":2},{"i":"kcbus:01002_RIT","d":"20270204","t":2},{"i":"kcbus:01002_RIT","d":"20270205","t":2},{"i":"kcbus:01002_RIT","d":"20270208","t":2},{"i":"kcbus:01002_RIT","d":"20270209","t":2},{"i":"kcbus:01002_RIT","d":"20270210","t":2},{"i":"kcbus:01002_RIT","d":"20270211","t":2},{"i":"kcbus:01002_RIT","d":"20270212","t":2},{"i":"kcbus:01002_RIT","d":"20270215","t":2},{"i":"kcbus:01002_RIT","d":"20270216","t":2},{"i":"kcbus:01002_RIT","d":"20270217","t":2},{"i":"kcbus:01002_RIT","d":"20270218","t":2},{"i":"kcbus:01002_RIT","d":"20270219","t":2},{"i":"kcbus:01002_RIT","d":"20270222","t":2},{"i":"kcbus:01002_RIT","d":"20270223","t":2},{"i":"kcbus:01002_RIT","d":"20270224","t":2},{"i":"kcbus:01002_RIT","d":"20270225","t":2},{"i":"kcbus:01002_RIT","d":"20270226","t":2},{"i":"kcbus:01002_RIT","d":"20270301","t":2},{"i":"kcbus:01002_RIT","d":"20270302","t":2},{"i":"kcbus:01002_RIT","d":"20270303","t":2},{"i":"kcbus:01002_RIT","d":"20270304","t":2},{"i":"kcbus:01002_RIT","d":"20270305","t":2},{"i":"kcbus:01002_RIT","d":"20270308","t":2},{"i":"kcbus:01002_RIT","d":"20270309","t":2},{"i":"kcbus:01002_RIT","d":"20270310","t":2},{"i":"kcbus:01002_RIT","d":"20270311","t":2},{"i":"kcbus:01002_RIT","d":"20270312","t":2},{"i":"kcbus:01002_RIT","d":"20270315","t":2},{"i":"kcbus:01002_RIT","d":"20270316","t":2},{"i":"kcbus:01002_RIT","d":"20270317","t":2},{"i":"kcbus:01002_RIT","d":"20270318","t":2},{"i":"kcbus:01002_RIT","d":"20270319","t":2},{"i":"kcbus:01002_RIT","d":"20270322","t":2},{"i":"kcbus:01002_RIT","d":"20270323","t":2},{"i":"kcbus:01002_RIT","d":"20270324","t":2},{"i":"kcbus:01002_RIT","d":"20270325","t":2},{"i":"kcbus:01002_RIT","d":"20270326","t":2},{"i":"kcbus:01002_RIT","d":"20270329","t":2},{"i":"kcbus:01002_RIT","d":"20270330","t":2},{"i":"kcbus:01002_RIT","d":"20270331","t":2},{"i":"kcbus:01003_KSU","d":"20260320","t":2},{"i":"kcbus:01003_KSU","d":"20260323","t":2},{"i":"kcbus:01003_KSU","d":"20260324","t":2},{"i":"kcbus:01003_KSU","d":"20260325","t":2},{"i":"kcbus:01003_KSU","d":"20260326","t":2},{"i":"kcbus:01003_KSU","d":"20260327","t":2},{"i":"kcbus:01003_KSU","d":"20260330","t":2},{"i":"kcbus:01003_KSU","d":"20260331","t":2},{"i":"kcbus:01003_KSU","d":"20260429","t":2},{"i":"kcbus:01003_KSU","d":"20260504","t":2},{"i":"kcbus:01003_KSU","d":"20260505","t":2},{"i":"kcbus:01003_KSU","d":"20260506","t":2},{"i":"kcbus:01003_KSU","d":"20260720","t":2},{"i":"kcbus:01003_KSU","d":"20260803","t":2},{"i":"kcbus:01003_KSU","d":"20260804","t":2},{"i":"kcbus:01003_KSU","d":"20260805","t":2},{"i":"kcbus:01003_KSU","d":"20260806","t":2},{"i":"kcbus:01003_KSU","d":"20260807","t":2},{"i":"kcbus:01003_KSU","d":"20260810","t":2},{"i":"kcbus:01003_KSU","d":"20260811","t":2},{"i":"kcbus:01003_KSU","d":"20260812","t":2},{"i":"kcbus:01003_KSU","d":"20260813","t":2},{"i":"kcbus:01003_KSU","d":"20260814","t":2},{"i":"kcbus:01003_KSU","d":"20260817","t":2},{"i":"kcbus:01003_KSU","d":"20260818","t":2},{"i":"kcbus:01003_KSU","d":"20260819","t":2},{"i":"kcbus:01003_KSU","d":"20260820","t":2},{"i":"kcbus:01003_KSU","d":"20260821","t":2},{"i":"kcbus:01003_KSU","d":"20260824","t":2},{"i":"kcbus:01003_KSU","d":"20260825","t":2},{"i":"kcbus:01003_KSU","d":"20260826","t":2},{"i":"kcbus:01003_KSU","d":"20260827","t":2},{"i":"kcbus:01003_KSU","d":"20260828","t":2},{"i":"kcbus:01003_KSU","d":"20260831","t":2},{"i":"kcbus:01003_KSU","d":"20260901","t":2},{"i":"kcbus:01003_KSU","d":"20260902","t":2},{"i":"kcbus:01003_KSU","d":"20260903","t":2},{"i":"kcbus:01003_KSU","d":"20260904","t":2},{"i":"kcbus:01003_KSU","d":"20260907","t":2},{"i":"kcbus:01003_KSU","d":"20260908","t":2},{"i":"kcbus:01003_KSU","d":"20260909","t":2},{"i":"kcbus:01003_KSU","d":"20260910","t":2},{"i":"kcbus:01003_KSU","d":"20260911","t":2},{"i":"kcbus:01003_KSU","d":"20260914","t":2},{"i":"kcbus:01003_KSU","d":"20260915","t":2},{"i":"kcbus:01003_KSU","d":"20260916","t":2},{"i":"kcbus:01003_KSU","d":"20260917","t":2},{"i":"kcbus:01003_KSU","d":"20260918","t":2},{"i":"kcbus:01003_KSU","d":"20260921","t":2},{"i":"kcbus:01003_KSU","d":"20260922","t":2},{"i":"kcbus:01003_KSU","d":"20260923","t":2},{"i":"kcbus:01003_KSU","d":"20260924","t":2},{"i":"kcbus:01003_KSU","d":"20260925","t":2},{"i":"kcbus:01003_KSU","d":"20261012","t":2},{"i":"kcbus:01003_KSU","d":"20261102","t":2},{"i":"kcbus:01003_KSU","d":"20261103","t":2},{"i":"kcbus:01003_KSU","d":"20261104","t":2},{"i":"kcbus:01003_KSU","d":"20261123","t":2},{"i":"kcbus:01003_KSU","d":"20261229","t":2},{"i":"kcbus:01003_KSU","d":"20261230","t":2},{"i":"kcbus:01003_KSU","d":"20261231","t":2},{"i":"kcbus:01003_KSU","d":"20270101","t":2},{"i":"kcbus:01003_KSU","d":"20270104","t":2},{"i":"kcbus:01003_KSU","d":"20270105","t":2},{"i":"kcbus:01003_KSU","d":"20270111","t":2},{"i":"kcbus:01003_KSU","d":"20270126","t":2},{"i":"kcbus:01003_KSU","d":"20270127","t":2},{"i":"kcbus:01003_KSU","d":"20270128","t":2},{"i":"kcbus:01003_KSU","d":"20270129","t":2},{"i":"kcbus:01003_KSU","d":"20270201","t":2},{"i":"kcbus:01003_KSU","d":"20270202","t":2},{"i":"kcbus:01003_KSU","d":"20270203","t":2},{"i":"kcbus:01003_KSU","d":"20270204","t":2},{"i":"kcbus:01003_KSU","d":"20270205","t":2},{"i":"kcbus:01003_KSU","d":"20270208","t":2},{"i":"kcbus:01003_KSU","d":"20270209","t":2},{"i":"kcbus:01003_KSU","d":"20270210","t":2},{"i":"kcbus:01003_KSU","d":"20270211","t":2},{"i":"kcbus:01003_KSU","d":"20270212","t":2},{"i":"kcbus:01003_KSU","d":"20270215","t":2},{"i":"kcbus:01003_KSU","d":"20270216","t":2},{"i":"kcbus:01003_KSU","d":"20270217","t":2},{"i":"kcbus:01003_KSU","d":"20270218","t":2},{"i":"kcbus:01003_KSU","d":"20270219","t":2},{"i":"kcbus:01003_KSU","d":"20270222","t":2},{"i":"kcbus:01003_KSU","d":"20270223","t":2},{"i":"kcbus:01003_KSU","d":"20270224","t":2},{"i":"kcbus:01003_KSU","d":"20270225","t":2},{"i":"kcbus:01003_KSU","d":"20270226","t":2},{"i":"kcbus:01003_KSU","d":"20270301","t":2},{"i":"kcbus:01003_KSU","d":"20270302","t":2},{"i":"kcbus:01003_KSU","d":"20270303","t":2},{"i":"kcbus:01003_KSU","d":"20270304","t":2},{"i":"kcbus:01003_KSU","d":"20270305","t":2},{"i":"kcbus:01003_KSU","d":"20270308","t":2},{"i":"kcbus:01003_KSU","d":"20270309","t":2},{"i":"kcbus:01003_KSU","d":"20270310","t":2},{"i":"kcbus:01003_KSU","d":"20270311","t":2},{"i":"kcbus:01003_KSU","d":"20270312","t":2},{"i":"kcbus:01003_KSU","d":"20270315","t":2},{"i":"kcbus:01003_KSU","d":"20270316","t":2},{"i":"kcbus:01003_KSU","d":"20270317","t":2},{"i":"kcbus:01003_KSU","d":"20270318","t":2},{"i":"kcbus:01003_KSU","d":"20270319","t":2},{"i":"kcbus:01003_KSU","d":"20270322","t":2},{"i":"kcbus:01003_KSU","d":"20270323","t":2},{"i":"kcbus:01003_KSU","d":"20270324","t":2},{"i":"kcbus:01003_KSU","d":"20270325","t":2},{"i":"kcbus:01003_KSU","d":"20270326","t":2},{"i":"kcbus:01003_KSU","d":"20270329","t":2},{"i":"kcbus:01003_KSU","d":"20270330","t":2},{"i":"kcbus:01003_KSU","d":"20270331","t":2},{"i":"kcbus:01004_BUK","d":"20260320","t":2},{"i":"kcbus:01004_BUK","d":"20260323","t":2},{"i":"kcbus:01004_BUK","d":"20260324","t":2},{"i":"kcbus:01004_BUK","d":"20260325","t":2},{"i":"kcbus:01004_BUK","d":"20260429","t":2},{"i":"kcbus:01004_BUK","d":"20260504","t":2},{"i":"kcbus:01004_BUK","d":"20260505","t":2},{"i":"kcbus:01004_BUK","d":"20260506","t":2},{"i":"kcbus:01004_BUK","d":"20260720","t":2},{"i":"kcbus:01004_BUK","d":"20260804","t":2},{"i":"kcbus:01004_BUK","d":"20260805","t":2},{"i":"kcbus:01004_BUK","d":"20260806","t":2},{"i":"kcbus:01004_BUK","d":"20260807","t":2},{"i":"kcbus:01004_BUK","d":"20260810","t":2},{"i":"kcbus:01004_BUK","d":"20260811","t":2},{"i":"kcbus:01004_BUK","d":"20260812","t":2},{"i":"kcbus:01004_BUK","d":"20260813","t":2},{"i":"kcbus:01004_BUK","d":"20260814","t":2},{"i":"kcbus:01004_BUK","d":"20260817","t":2},{"i":"kcbus:01004_BUK","d":"20260818","t":2},{"i":"kcbus:01004_BUK","d":"20260819","t":2},{"i":"kcbus:01004_BUK","d":"20260820","t":2},{"i":"kcbus:01004_BUK","d":"20260821","t":2},{"i":"kcbus:01004_BUK","d":"20260824","t":2},{"i":"kcbus:01004_BUK","d":"20260825","t":2},{"i":"kcbus:01004_BUK","d":"20260826","t":2},{"i":"kcbus:01004_BUK","d":"20260827","t":2},{"i":"kcbus:01004_BUK","d":"20260828","t":2},{"i":"kcbus:01004_BUK","d":"20260831","t":2},{"i":"kcbus:01004_BUK","d":"20260901","t":2},{"i":"kcbus:01004_BUK","d":"20260902","t":2},{"i":"kcbus:01004_BUK","d":"20260903","t":2},{"i":"kcbus:01004_BUK","d":"20260904","t":2},{"i":"kcbus:01004_BUK","d":"20260907","t":2},{"i":"kcbus:01004_BUK","d":"20260908","t":2},{"i":"kcbus:01004_BUK","d":"20260909","t":2},{"i":"kcbus:01004_BUK","d":"20260910","t":2},{"i":"kcbus:01004_BUK","d":"20260911","t":2},{"i":"kcbus:01004_BUK","d":"20260914","t":2},{"i":"kcbus:01004_BUK","d":"20260915","t":2},{"i":"kcbus:01004_BUK","d":"20260916","t":2},{"i":"kcbus:01004_BUK","d":"20260917","t":2},{"i":"kcbus:01004_BUK","d":"20260921","t":2},{"i":"kcbus:01004_BUK","d":"20260922","t":2},{"i":"kcbus:01004_BUK","d":"20260923","t":2},{"i":"kcbus:01004_BUK","d":"20261012","t":2},{"i":"kcbus:01004_BUK","d":"20261103","t":2},{"i":"kcbus:01004_BUK","d":"20261123","t":2},{"i":"kcbus:01004_BUK","d":"20261224","t":2},{"i":"kcbus:01004_BUK","d":"20261225","t":2},{"i":"kcbus:01004_BUK","d":"20261228","t":2},{"i":"kcbus:01004_BUK","d":"20261229","t":2},{"i":"kcbus:01004_BUK","d":"20261230","t":2},{"i":"kcbus:01004_BUK","d":"20261231","t":2},{"i":"kcbus:01004_BUK","d":"20270101","t":2},{"i":"kcbus:01004_BUK","d":"20270104","t":2},{"i":"kcbus:01004_BUK","d":"20270105","t":2},{"i":"kcbus:01004_BUK","d":"20270111","t":2},{"i":"kcbus:01004_BUK","d":"20270201","t":2},{"i":"kcbus:01004_BUK","d":"20270202","t":2},{"i":"kcbus:01004_BUK","d":"20270203","t":2},{"i":"kcbus:01004_BUK","d":"20270204","t":2},{"i":"kcbus:01004_BUK","d":"20270205","t":2},{"i":"kcbus:01004_BUK","d":"20270208","t":2},{"i":"kcbus:01004_BUK","d":"20270209","t":2},{"i":"kcbus:01004_BUK","d":"20270210","t":2},{"i":"kcbus:01004_BUK","d":"20270211","t":2},{"i":"kcbus:01004_BUK","d":"20270212","t":2},{"i":"kcbus:01004_BUK","d":"20270215","t":2},{"i":"kcbus:01004_BUK","d":"20270216","t":2},{"i":"kcbus:01004_BUK","d":"20270217","t":2},{"i":"kcbus:01004_BUK","d":"20270218","t":2},{"i":"kcbus:01004_BUK","d":"20270219","t":2},{"i":"kcbus:01004_BUK","d":"20270222","t":2},{"i":"kcbus:01004_BUK","d":"20270223","t":2},{"i":"kcbus:01004_BUK","d":"20270224","t":2},{"i":"kcbus:01004_BUK","d":"20270225","t":2},{"i":"kcbus:01004_BUK","d":"20270226","t":2},{"i":"kcbus:01004_BUK","d":"20270301","t":2},{"i":"kcbus:01004_BUK","d":"20270302","t":2},{"i":"kcbus:01004_BUK","d":"20270303","t":2},{"i":"kcbus:01004_BUK","d":"20270304","t":2},{"i":"kcbus:01004_BUK","d":"20270305","t":2},{"i":"kcbus:01004_BUK","d":"20270308","t":2},{"i":"kcbus:01004_BUK","d":"20270309","t":2},{"i":"kcbus:01004_BUK","d":"20270310","t":2},{"i":"kcbus:01004_BUK","d":"20270311","t":2},{"i":"kcbus:01004_BUK","d":"20270312","t":2},{"i":"kcbus:01004_BUK","d":"20270315","t":2},{"i":"kcbus:01004_BUK","d":"20270316","t":2},{"i":"kcbus:01004_BUK","d":"20270317","t":2},{"i":"kcbus:01004_BUK","d":"20270318","t":2},{"i":"kcbus:01004_BUK","d":"20270319","t":2},{"i":"kcbus:01004_BUK","d":"20270322","t":2},{"i":"kcbus:01004_BUK","d":"20270323","t":2},{"i":"kcbus:01004_BUK","d":"20270324","t":2},{"i":"kcbus:01005_MSN","d":"20260320","t":2},{"i":"kcbus:01005_MSN","d":"20260325","t":2},{"i":"kcbus:01005_MSN","d":"20260326","t":2},{"i":"kcbus:01005_MSN","d":"20260327","t":2},{"i":"kcbus:01005_MSN","d":"20260330","t":2},{"i":"kcbus:01005_MSN","d":"20260331","t":2},{"i":"kcbus:01005_MSN","d":"20260401","t":2},{"i":"kcbus:01005_MSN","d":"20260402","t":2},{"i":"kcbus:01005_MSN","d":"20260403","t":2},{"i":"kcbus:01005_MSN","d":"20260406","t":2},{"i":"kcbus:01005_MSN","d":"20260407","t":2},{"i":"kcbus:01005_MSN","d":"20260408","t":2},{"i":"kcbus:01005_MSN","d":"20260409","t":2},{"i":"kcbus:01005_MSN","d":"20260429","t":2},{"i":"kcbus:01005_MSN","d":"20260504","t":2},{"i":"kcbus:01005_MSN","d":"20260505","t":2},{"i":"kcbus:01005_MSN","d":"20260506","t":2},{"i":"kcbus:01005_MSN","d":"20260720","t":2},{"i":"kcbus:01005_MSN","d":"20260723","t":2},{"i":"kcbus:01005_MSN","d":"20260724","t":2},{"i":"kcbus:01005_MSN","d":"20260727","t":2},{"i":"kcbus:01005_MSN","d":"20260728","t":2},{"i":"kcbus:01005_MSN","d":"20260729","t":2},{"i":"kcbus:01005_MSN","d":"20260730","t":2},{"i":"kcbus:01005_MSN","d":"20260731","t":2},{"i":"kcbus:01005_MSN","d":"20260803","t":2},{"i":"kcbus:01005_MSN","d":"20260804","t":2},{"i":"kcbus:01005_MSN","d":"20260805","t":2},{"i":"kcbus:01005_MSN","d":"20260806","t":2},{"i":"kcbus:01005_MSN","d":"20260807","t":2},{"i":"kcbus:01005_MSN","d":"20260810","t":2},{"i":"kcbus:01005_MSN","d":"20260811","t":2},{"i":"kcbus:01005_MSN","d":"20260812","t":2},{"i":"kcbus:01005_MSN","d":"20260813","t":2},{"i":"kcbus:01005_MSN","d":"20260814","t":2},{"i":"kcbus:01005_MSN","d":"20260817","t":2},{"i":"kcbus:01005_MSN","d":"20260818","t":2},{"i":"kcbus:01005_MSN","d":"20260819","t":2},{"i":"kcbus:01005_MSN","d":"20260820","t":2},{"i":"kcbus:01005_MSN","d":"20260821","t":2},{"i":"kcbus:01005_MSN","d":"20260824","t":2},{"i":"kcbus:01005_MSN","d":"20260825","t":2},{"i":"kcbus:01005_MSN","d":"20260921","t":2},{"i":"kcbus:01005_MSN","d":"20260922","t":2},{"i":"kcbus:01005_MSN","d":"20260923","t":2},{"i":"kcbus:01005_MSN","d":"20261012","t":2},{"i":"kcbus:01005_MSN","d":"20261103","t":2},{"i":"kcbus:01005_MSN","d":"20261123","t":2},{"i":"kcbus:01005_MSN","d":"20261225","t":2},{"i":"kcbus:01005_MSN","d":"20261228","t":2},{"i":"kcbus:01005_MSN","d":"20261229","t":2},{"i":"kcbus:01005_MSN","d":"20261230","t":2},{"i":"kcbus:01005_MSN","d":"20261231","t":2},{"i":"kcbus:01005_MSN","d":"20270101","t":2},{"i":"kcbus:01005_MSN","d":"20270104","t":2},{"i":"kcbus:01005_MSN","d":"20270105","t":2},{"i":"kcbus:01005_MSN","d":"20270111","t":2},{"i":"kcbus:01005_MSN","d":"20270211","t":2},{"i":"kcbus:01005_MSN","d":"20270223","t":2},{"i":"kcbus:01005_MSN","d":"20270322","t":2},{"i":"kcbus:01005_MSN","d":"20270325","t":2},{"i":"kcbus:01005_MSN","d":"20270326","t":2},{"i":"kcbus:01005_MSN","d":"20270329","t":2},{"i":"kcbus:01005_MSN","d":"20270330","t":2},{"i":"kcbus:01005_MSN","d":"20270331","t":2},{"i":"kcbus:02001","d":"20260320","t":1},{"i":"kcbus:02001","d":"20260429","t":1},{"i":"kcbus:02001","d":"20260504","t":1},{"i":"kcbus:02001","d":"20260505","t":1},{"i":"kcbus:02001","d":"20260506","t":1},{"i":"kcbus:02001","d":"20260720","t":1},{"i":"kcbus:02001","d":"20260811","t":1},{"i":"kcbus:02001","d":"20260814","t":1},{"i":"kcbus:02001","d":"20260815","t":1},{"i":"kcbus:02001","d":"20260921","t":1},{"i":"kcbus:02001","d":"20260922","t":1},{"i":"kcbus:02001","d":"20260923","t":1},{"i":"kcbus:02001","d":"20261012","t":1},{"i":"kcbus:02001","d":"20261103","t":1},{"i":"kcbus:02001","d":"20261123","t":1},{"i":"kcbus:02001","d":"20261229","t":1},{"i":"kcbus:02001","d":"20261230","t":1},{"i":"kcbus:02001","d":"20261231","t":1},{"i":"kcbus:02001","d":"20270101","t":1},{"i":"kcbus:02001","d":"20270102","t":1},{"i":"kcbus:02001","d":"20270111","t":1},{"i":"kcbus:02001","d":"20270211","t":1},{"i":"kcbus:02001","d":"20270223","t":1},{"i":"kcbus:02001","d":"20270322","t":1},{"i":"kcbus:02001_A","d":"20260322","t":2},{"i":"kcbus:02001_A","d":"20260329","t":2},{"i":"kcbus:02001_A","d":"20260405","t":2},{"i":"kcbus:02001_A","d":"20260429","t":1},{"i":"kcbus:02001_A","d":"20260504","t":1},{"i":"kcbus:02001_A","d":"20260505","t":1},{"i":"kcbus:02001_A","d":"20260506","t":1},{"i":"kcbus:02001_C","d":"20260320","t":1},{"i":"kcbus:02001_C","d":"20260322","t":1},{"i":"kcbus:02001_C","d":"20260329","t":1},{"i":"kcbus:02001_C","d":"20260405","t":1},{"i":"kcbus:02001_GYB","d":"20260320","t":1},{"i":"kcbus:02001_GYB","d":"20260429","t":1},{"i":"kcbus:02001_GYB","d":"20260504","t":1},{"i":"kcbus:02001_GYB","d":"20260505","t":1},{"i":"kcbus:02001_GYB","d":"20260506","t":1},{"i":"kcbus:02001_GYB","d":"20260720","t":1},{"i":"kcbus:02001_GYB","d":"20260811","t":1},{"i":"kcbus:02001_GYB","d":"20260814","t":1},{"i":"kcbus:02001_GYB","d":"20260815","t":1},{"i":"kcbus:02001_GYB","d":"20260921","t":1},{"i":"kcbus:02001_GYB","d":"20260922","t":1},{"i":"kcbus:02001_GYB","d":"20260923","t":1},{"i":"kcbus:02001_GYB","d":"20261012","t":1},{"i":"kcbus:02001_GYB","d":"20261103","t":1},{"i":"kcbus:02001_GYB","d":"20261123","t":1},{"i":"kcbus:02001_GYB","d":"20261229","t":1},{"i":"kcbus:02001_GYB","d":"20261230","t":1},{"i":"kcbus:02001_GYB","d":"20261231","t":1},{"i":"kcbus:02001_GYB","d":"20270101","t":1},{"i":"kcbus:02001_GYB","d":"20270102","t":1},{"i":"kcbus:02001_GYB","d":"20270111","t":1},{"i":"kcbus:02001_GYB","d":"20270211","t":1},{"i":"kcbus:02001_GYB","d":"20270223","t":1},{"i":"kcbus:02001_GYB","d":"20270322","t":1},{"i":"kcbus:03001","d":"20260815","t":2},{"i":"kcbus:03001","d":"20270102","t":2},{"i":"kcbus:03001_A","d":"20260321","t":2},{"i":"kcbus:03001_A","d":"20260328","t":2},{"i":"kcbus:03001_A","d":"20260404","t":2},{"i":"kcbus:03001_C","d":"20260321","t":1},{"i":"kcbus:03001_C","d":"20260328","t":1},{"i":"kcbus:03001_C","d":"20260404","t":1},{"i":"kcbus:03001_GYB","d":"20260815","t":2},{"i":"kcbus:03001_GYB","d":"20270102","t":2},{"i":"kcbus:SRV_8_10600_01","d":"20260322","t":1},{"i":"kcbus:SRV_8_10600_01_C","d":"20260322","t":1},{"i":"kcbus:SRV_8_10600_02","d":"20260320","t":1},{"i":"kcbus:SRV_8_10600_02","d":"20260321","t":1},{"i":"kcbus:SRV_8_10600_02","d":"20260328","t":1},{"i":"kcbus:SRV_8_10600_02","d":"20260329","t":1},{"i":"kcbus:SRV_8_10600_02","d":"20260404","t":1},{"i":"kcbus:SRV_8_10600_02","d":"20260405","t":1},{"i":"kcbus:SRV_8_10600_02","d":"20260411","t":1},{"i":"kcbus:SRV_8_10600_02","d":"20260412","t":1},{"i":"kcbus:SRV_8_10600_02_A","d":"20260411","t":1},{"i":"kcbus:SRV_8_10600_02_A","d":"20260412","t":1},{"i":"kcbus:SRV_8_10600_02_C","d":"20260320","t":1},{"i":"kcbus:SRV_8_10600_02_C","d":"20260321","t":1},{"i":"kcbus:SRV_8_10600_02_C","d":"20260328","t":1},{"i":"kcbus:SRV_8_10600_02_C","d":"20260329","t":1},{"i":"kcbus:SRV_8_10600_02_C","d":"20260404","t":1},{"i":"kcbus:SRV_8_10600_02_C","d":"20260405","t":1}]}