{
  "sourceName": "toei-bus",
  "type": "gtfs",
  "status": "ok",
  "downloadedAt": "2026-04-28T03:31:26.777Z",
  "url": "https://api-public.odpt.org/api/v4/files/Toei/data/ToeiBus-GTFS.zip",
  "size": 7071235,
  "contentType": "application/octet-stream",
  "durationMs": 4717,
  "archivePath": "workspace/_archives/gtfs/toei-bus/ToeiBus-GTFS_20260428-033131.zip",
  "extractedFiles": [
    {
      "name": "agency.txt",
      "size": 185
    },
    {
      "name": "agency_jp.txt",
      "size": 218
    },
    {
      "name": "attributions.txt",
      "size": 290
    },
    {
      "name": "office_jp.txt",
      "size": 451
    },
    {
      "name": "stops.txt",
      "size": 776676
    },
    {
      "name": "translations.txt",
      "size": 689596
    },
    {
      "name": "routes.txt",
      "size": 17900
    },
    {
      "name": "trips.txt",
      "size": 3536827
    },
    {
      "name": "stop_times.txt",
      "size": 69651242
    },
    {
      "name": "calendar.txt",
      "size": 2428
    },
    {
      "name": "calendar_dates.txt",
      "size": 3955
    },
    {
      "name": "feed_info.txt",
      "size": 182
    },
    {
      "name": "shapes.txt",
      "size": 1433899
    },
    {
      "name": "fare_attributes.txt",
      "size": 1527
    },
    {
      "name": "fare_rules.txt",
      "size": 745481
    }
  ],
  "feedInfo": {
    "publisherName": "東京都交通局",
    "publisherUrl": "https://www.kotsu.metro.tokyo.jp/",
    "lang": "ja",
    "startDate": "20260428",
    "endDate": "20290427",
    "version": "20260428_030752"
  }
}
