[{"i":"ktbus:10000","s":"1号路線 吉祥寺東循環","l":"ＭＵ１吉祥寺駅循環（迂）","t":3,"c":"FFBF00","tc":"0A0A0A","ai":"ktbus:8011201001183"},{"i":"ktbus:10001","s":"2号路線 吉祥寺北西循環","l":"ＭＵ吉祥寺循環２号","t":3,"c":"0052B5","tc":"FFFFFF","ai":"ktbus:8011201001183"},{"i":"ktbus:10002","s":"6号路線 三鷹・吉祥寺循環","l":"ムーバス６号（行き）","t":3,"c":"F27000","tc":"FFFFFF","ai":"ktbus:8011201001183"},{"i":"ktbus:10003","s":"K05","l":"せせらぎ公園","t":3,"c":"E60013","tc":"FFFFFF","ai":"ktbus:8011201001183"},{"i":"ktbus:10004","s":"K06","l":"せせらぎ公園（白鷺経由）","t":3,"c":"E60013","tc":"FFFFFF","ai":"ktbus:8011201001183"},{"i":"ktbus:10005","s":"すぎ丸","l":"すぎ丸：西荻〜久我山","t":3,"c":"E60013","tc":"FFFFFF","ai":"ktbus:8011201001183"},{"i":"ktbus:10006","s":"三鷹北西","l":"ＭＵ三鷹４号（公園通過）","t":3,"c":"E60013","tc":"FFFFFF","ai":"ktbus:8011201001183"},{"i":"ktbus:10007","s":"中０１","l":"中野駅〜野方","t":3,"c":"E60013","tc":"FFFFFF","ai":"ktbus:8011201001183"},{"i":"ktbus:10008","s":"中０３","l":"中野駅〜練馬駅　中練","t":3,"c":"E60013","tc":"FFFFFF","ai":"ktbus:8011201001183"},{"i":"ktbus:10009","s":"中１０","l":"中野駅〜丸山（営）１０Ｉ","t":3,"c":"E60013","tc":"FFFFFF","ai":"ktbus:8011201001183"},{"i":"ktbus:10010","s":"中１２","l":"中野駅〜江古田駅：１２","t":3,"c":"E60013","tc":"FFFFFF","ai":"ktbus:8011201001183"},{"i":"ktbus:10011","s":"中１２−２","l":"中野駅〜江古田駅：１２−２","t":3,"c":"E60013","tc":"FFFFFF","ai":"ktbus:8011201001183"},{"i":"ktbus:10012","s":"中２０","l":"中野駅〜丸山（営）２０サ","t":3,"c":"E60013","tc":"FFFFFF","ai":"ktbus:8011201001183"},{"i":"ktbus:10013","s":"中２４","l":"中村橋〜中野駅","t":3,"c":"E60013","tc":"FFFFFF","ai":"ktbus:8011201001183"},{"i":"ktbus:10014","s":"中２７","l":"中野駅〜江古田の森","t":3,"c":"E60013","tc":"FFFFFF","ai":"ktbus:8011201001183"},{"i":"ktbus:10015","s":"中３０","l":"丸山（営）〜中野駅３０Ｉ","t":3,"c":"E60013","tc":"FFFFFF","ai":"ktbus:8011201001183"},{"i":"ktbus:10016","s":"中３５","l":"中野駅〜五日市（営）","t":3,"c":"E60013","tc":"FFFFFF","ai":"ktbus:8011201001183"},{"i":"ktbus:10017","s":"中３６","l":"中野駅〜吉祥寺駅","t":3,"c":"E60013","tc":"FFFFFF","ai":"ktbus:8011201001183"},{"i":"ktbus:10018","s":"中４１","l":"中野駅〜江古田駅：４１","t":3,"c":"E60013","tc":"FFFFFF","ai":"ktbus:8011201001183"},{"i":"ktbus:10019","s":"中４３","l":"江古田駅〜中野駅（新道）","t":3,"c":"E60013","tc":"FFFFFF","ai":"ktbus:8011201001183"},{"i":"ktbus:10020","s":"中４５","l":"中野駅〜丸山営業所：４５","t":3,"c":"E60013","tc":"FFFFFF","ai":"ktbus:8011201001183"},{"i":"ktbus:10021","s":"吉５０","l":"吉祥寺駅〜成蹊学園","t":3,"c":"E60013","tc":"FFFFFF","ai":"ktbus:8011201001183"},{"i":"ktbus:10022","s":"吉５０ 直行","l":"直行　吉祥寺駅〜成蹊学園","t":3,"c":"E60013","tc":"FFFFFF","ai":"ktbus:8011201001183"},{"i":"ktbus:10023","s":"吉５１","l":"吉祥寺〜武蔵野（営）Ｋ","t":3,"c":"E60013","tc":"FFFFFF","ai":"ktbus:8011201001183"},{"i":"ktbus:10024","s":"吉５２","l":"電通裏〜吉祥寺駅","t":3,"c":"000000","tc":"FFFFFF","ai":"ktbus:8011201001183"},{"i":"ktbus:10025","s":"吉５３","l":"吉祥寺駅〜柳沢駅","t":3,"c":"E60013","tc":"FFFFFF","ai":"ktbus:8011201001183"},{"i":"ktbus:10026","s":"吉５４","l":"吉祥寺駅〜武蔵野市役所","t":3,"c":"E60013","tc":"FFFFFF","ai":"ktbus:8011201001183"},{"i":"ktbus:10027","s":"吉５５","l":"吉祥寺駅〜柳沢駅：市","t":3,"c":"E60013","tc":"FFFFFF","ai":"ktbus:8011201001183"},{"i":"ktbus:10028","s":"吉７２","l":"桜堤団地〜吉祥寺駅","t":3,"c":"E60013","tc":"FFFFFF","ai":"ktbus:8011201001183"},{"i":"ktbus:10029","s":"吉７３","l":"吉祥寺駅〜向台町５","t":3,"c":"E60013","tc":"FFFFFF","ai":"ktbus:8011201001183"},{"i":"ktbus:10030","s":"吉７４","l":"吉祥寺駅〜関前西公園","t":3,"c":"E60013","tc":"FFFFFF","ai":"ktbus:8011201001183"},{"i":"ktbus:10031","s":"吉７５","l":"吉祥寺駅〜ヴィ","t":3,"c":"E60013","tc":"FFFFFF","ai":"ktbus:8011201001183"},{"i":"ktbus:10032","s":"吉８０","l":"青梅街道（営）〜吉祥寺駅","t":3,"c":"E60013","tc":"FFFFFF","ai":"ktbus:8011201001183"},{"i":"ktbus:10033","s":"吉８１","l":"吉祥寺駅〜上石神井駅","t":3,"c":"E60013","tc":"FFFFFF","ai":"ktbus:8011201001183"},{"i":"ktbus:10034","s":"境１２","l":"武蔵境駅〜向台町５","t":3,"c":"E60013","tc":"FFFFFF","ai":"ktbus:8011201001183"},{"i":"ktbus:10035","s":"境１６","l":"武蔵境駅〜花小金井南口","t":3,"c":"E60013","tc":"FFFFFF","ai":"ktbus:8011201001183"},{"i":"ktbus:10036","s":"境１７","l":"武蔵境〜ヴィ","t":3,"c":"E60013","tc":"FFFFFF","ai":"ktbus:8011201001183"},{"i":"ktbus:10037","s":"境１７−１","l":"武蔵境（浄〜武蔵野（営）","t":3,"c":"E60013","tc":"FFFFFF","ai":"ktbus:8011201001183"},{"i":"ktbus:10038","s":"境１７−２","l":"武蔵野（営）〜武蔵境（浄","t":3,"c":"E60013","tc":"FFFFFF","ai":"ktbus:8011201001183"},{"i":"ktbus:10039","s":"宿０１","l":"新宿西口〜小滝橋","t":3,"c":"E60013","tc":"FFFFFF","ai":"ktbus:8011201001183"},{"i":"ktbus:10040","s":"宿０１−１","l":"小滝橋〜新宿西口（７０）","t":3,"c":"E60013","tc":"FFFFFF","ai":"ktbus:8011201001183"},{"i":"ktbus:10041","s":"宿０２","l":"新宿西口〜丸山営業所","t":3,"c":"FF0FBF","tc":"000000","ai":"ktbus:8011201001183"},{"i":"ktbus:10042","s":"宿０４","l":"阿佐谷営〜新宿西口（０４","t":3,"c":"E60013","tc":"FFFFFF","ai":"ktbus:8011201001183"},{"i":"ktbus:10043","s":"宿０５","l":"野方駅〜新宿駅西口","t":3,"c":"E60013","tc":"FFFFFF","ai":"ktbus:8011201001183"},{"i":"ktbus:10044","s":"宿０８","l":"中野駅〜新宿駅西口","t":3,"c":"E60013","tc":"FFFFFF","ai":"ktbus:8011201001183"},{"i":"ktbus:10045","s":"新０２","l":"新高円寺駅〜永福町（松）","t":3,"c":"E60013","tc":"FFFFFF","ai":"ktbus:8011201001183"},{"i":"ktbus:10046","s":"池１１","l":"中野駅〜池袋駅","t":3,"c":"E60013","tc":"FFFFFF","ai":"ktbus:8011201001183"},{"i":"ktbus:10049","s":"烏０１","l":"千歳烏山駅〜久我山病院","t":3,"c":"E60013","tc":"FFFFFF","ai":"ktbus:8011201001183"},{"i":"ktbus:10050","s":"百０１","l":"高田馬場駅〜東中野駅西口","t":3,"c":"4DFB41","tc":"000000","ai":"ktbus:8011201001183"},{"i":"ktbus:10051","s":"練２１","l":"練馬駅〜練馬駅","t":3,"c":"E60013","tc":"FFFFFF","ai":"ktbus:8011201001183"},{"i":"ktbus:10052","s":"花２０","l":"花小金井駅南口〜損保ジャパン（直行）","t":3,"c":"E60013","tc":"FFFFFF","ai":"ktbus:8011201001183"},{"i":"ktbus:10053","s":"花２１","l":"花小金井駅南口〜向台町五丁目","t":3,"c":"E60013","tc":"FFFFFF","ai":"ktbus:8011201001183"},{"i":"ktbus:10054","s":"荻０４","l":"荻窪駅〜阿佐谷営業所","t":3,"c":"E60013","tc":"FFFFFF","ai":"ktbus:8011201001183"},{"i":"ktbus:10055","s":"荻０５","l":"荻窪駅〜白鷺１：日","t":3,"c":"E60013","tc":"FFFFFF","ai":"ktbus:8011201001183"},{"i":"ktbus:10056","s":"荻０６","l":"荻窪駅〜中村橋駅","t":3,"c":"E60013","tc":"FFFFFF","ai":"ktbus:8011201001183"},{"i":"ktbus:10057","s":"荻０７","l":"荻窪駅〜練馬駅","t":3,"c":"E60013","tc":"FFFFFF","ai":"ktbus:8011201001183"},{"i":"ktbus:10058","s":"荻１０","l":"荻窪駅〜下井草駅","t":3,"c":"E60013","tc":"FFFFFF","ai":"ktbus:8011201001183"},{"i":"ktbus:10059","s":"荻１１","l":"荻窪駅〜石神井公園駅","t":3,"c":"E60013","tc":"FFFFFF","ai":"ktbus:8011201001183"},{"i":"ktbus:10060","s":"荻１２","l":"荻窪駅〜井荻駅","t":3,"c":"E60013","tc":"FFFFFF","ai":"ktbus:8011201001183"},{"i":"ktbus:10061","s":"荻３０","l":"荻窪駅〜青梅街道営業所Ｏ","t":3,"c":"E60013","tc":"FFFFFF","ai":"ktbus:8011201001183"},{"i":"ktbus:10062","s":"荻３１","l":"ＰＲ荻窪〜荻窪駅","t":3,"c":"E60013","tc":"FFFFFF","ai":"ktbus:8011201001183"},{"i":"ktbus:10063","s":"荻３２","l":"荻窪駅〜武蔵関駅","t":3,"c":"E60013","tc":"FFFFFF","ai":"ktbus:8011201001183"},{"i":"ktbus:10064","s":"荻３３","l":"荻窪駅〜電通裏","t":3,"c":"E60013","tc":"FFFFFF","ai":"ktbus:8011201001183"},{"i":"ktbus:10065","s":"荻３４","l":"荻窪駅〜北裏（深）","t":3,"c":"E60013","tc":"FFFFFF","ai":"ktbus:8011201001183"},{"i":"ktbus:10066","s":"荻３５","l":"荻窪駅〜武蔵野大学","t":3,"c":"E60013","tc":"FFFFFF","ai":"ktbus:8011201001183"},{"i":"ktbus:10067","s":"荻３６","l":"荻窪駅〜南善福寺","t":3,"c":"E60013","tc":"FFFFFF","ai":"ktbus:8011201001183"},{"i":"ktbus:10068","s":"荻４０","l":"荻窪駅〜立教女学院","t":3,"c":"E60013","tc":"FFFFFF","ai":"ktbus:8011201001183"},{"i":"ktbus:10069","s":"荻５１","l":"荻窪南口〜シャレール荻窪","t":3,"c":"E60013","tc":"FFFFFF","ai":"ktbus:8011201001183"},{"i":"ktbus:10070","s":"荻５３","l":"五日市（営）〜荻窪南口川","t":3,"c":"E60013","tc":"FFFFFF","ai":"ktbus:8011201001183"},{"i":"ktbus:10071","s":"荻５３（深夜）","l":"荻窪南口〜五日市（営）深","t":3,"c":"E60013","tc":"FFFFFF","ai":"ktbus:8011201001183"},{"i":"ktbus:10072","s":"荻５４","l":"荻窪駅南口〜芦花公園駅","t":3,"c":"E60013","tc":"FFFFFF","ai":"ktbus:8011201001183"},{"i":"ktbus:10073","s":"荻５６","l":"荻窪駅南口〜年金機構","t":3,"c":"E60013","tc":"FFFFFF","ai":"ktbus:8011201001183"},{"i":"ktbus:10074","s":"荻５８","l":"荻窪駅南口〜北野","t":3,"c":"E60013","tc":"FFFFFF","ai":"ktbus:8011201001183"},{"i":"ktbus:10075","s":"荻６０","l":"荻窪駅南口〜宮前３丁目","t":3,"c":"E60013","tc":"FFFFFF","ai":"ktbus:8011201001183"},{"i":"ktbus:10076","s":"西０１","l":"青梅（営）〜西荻窪駅Ｋ","t":3,"c":"E60013","tc":"FFFFFF","ai":"ktbus:8011201001183"},{"i":"ktbus:10077","s":"西０２","l":"西荻窪駅〜上石神井駅","t":3,"c":"E60013","tc":"FFFFFF","ai":"ktbus:8011201001183"},{"i":"ktbus:10078","s":"西０３","l":"西荻窪駅〜大泉学園駅","t":3,"c":"E60013","tc":"FFFFFF","ai":"ktbus:8011201001183"},{"i":"ktbus:10080","s":"西１０","l":"西荻窪駅〜吉祥寺駅","t":3,"c":"E60013","tc":"FFFFFF","ai":"ktbus:8011201001183"},{"i":"ktbus:10081","s":"西２０","l":"立教女学院〜西荻窪駅","t":3,"c":"E60013","tc":"FFFFFF","ai":"ktbus:8011201001183"},{"i":"ktbus:10082","s":"西５０","l":"西荻窪駅〜井荻駅","t":3,"c":"E60013","tc":"FFFFFF","ai":"ktbus:8011201001183"},{"i":"ktbus:10083","s":"西５１","l":"西荻窪駅〜荻窪駅ＮＩ","t":3,"c":"E60013","tc":"FFFFFF","ai":"ktbus:8011201001183"},{"i":"ktbus:10084","s":"西５１−１","l":"荻窪駅〜青梅街道営　（今３ＮＩ）","t":3,"c":"E60013","tc":"FFFFFF","ai":"ktbus:8011201001183"},{"i":"ktbus:10085","s":"西５１−２","l":"青梅街道営〜荻窪駅（今３ＮＩ）","t":3,"c":"E60013","tc":"FFFFFF","ai":"ktbus:8011201001183"},{"i":"ktbus:10086","s":"赤３１","l":"高円寺駅北口〜赤羽駅東口","t":3,"c":"E60013","tc":"FFFFFF","ai":"ktbus:8011201001183"},{"i":"ktbus:10087","s":"阿０１","l":"阿佐ヶ谷駅〜中村橋駅","t":3,"c":"E60013","tc":"FFFFFF","ai":"ktbus:8011201001183"},{"i":"ktbus:10088","s":"阿０２","l":"阿佐谷駅〜白鷺１：Ａ","t":3,"c":"E60013","tc":"FFFFFF","ai":"ktbus:8011201001183"},{"i":"ktbus:10089","s":"阿０３","l":"阿佐ヶ谷駅〜中村橋駅０３","t":3,"c":"E60013","tc":"FFFFFF","ai":"ktbus:8011201001183"},{"i":"ktbus:10090","s":"阿０４","l":"阿佐ヶ谷駅〜白鷺１０４","t":3,"c":"E60013","tc":"FFFFFF","ai":"ktbus:8011201001183"},{"i":"ktbus:10091","s":"阿０５","l":"白鷺１丁目〜荻窪駅：阿","t":3,"c":"E60013","tc":"FFFFFF","ai":"ktbus:8011201001183"},{"i":"ktbus:10092","s":"阿４５","l":"阿佐ヶ谷駅〜中野駅","t":3,"c":"E60013","tc":"FFFFFF","ai":"ktbus:8011201001183"},{"i":"ktbus:10093","s":"阿５０","l":"阿佐ヶ谷駅〜石神井公園駅","t":3,"c":"E60013","tc":"FFFFFF","ai":"ktbus:8011201001183"},{"i":"ktbus:10094","s":"阿５１","l":"阿佐ヶ谷駅〜下井草駅","t":3,"c":"E60013","tc":"FFFFFF","ai":"ktbus:8011201001183"},{"i":"ktbus:10095","s":"高１０","l":"高円寺駅北口〜練馬駅　高１０","t":3,"c":"E60013","tc":"FFFFFF","ai":"ktbus:8011201001183"},{"i":"ktbus:10096","s":"高４３","l":"五日市（営）〜高円寺：馬","t":3,"c":"E60013","tc":"FFFFFF","ai":"ktbus:8011201001183"},{"i":"ktbus:10097","s":"高４５","l":"高円寺駅南口〜永福町（松","t":3,"c":"E60013","tc":"FFFFFF","ai":"ktbus:8011201001183"},{"i":"ktbus:10099","s":"高６０","l":"高円寺駅〜練馬駅：五","t":3,"c":"E60013","tc":"FFFFFF","ai":"ktbus:8011201001183"},{"i":"ktbus:10100","s":"高６３","l":"高円寺駅〜豊玉南住宅","t":3,"c":"E60013","tc":"FFFFFF","ai":"ktbus:8011201001183"},{"i":"ktbus:10101","s":"高７０","l":"丸山営業所〜高円寺駅","t":3,"c":"E60013","tc":"FFFFFF","ai":"ktbus:8011201001183"},{"i":"ktbus:10102","s":"鷹０１","l":"三鷹駅〜北裏","t":3,"c":"000000","tc":"FFFFFF","ai":"ktbus:8011201001183"},{"i":"ktbus:10103","s":"鷹０２","l":"三鷹駅〜武蔵関駅","t":3,"c":"000000","tc":"FFFFFF","ai":"ktbus:8011201001183"},{"i":"ktbus:10104","s":"鷹０３","l":"三鷹駅〜田無橋場","t":3,"c":"000000","tc":"FFFFFF","ai":"ktbus:8011201001183"},{"i":"ktbus:10105","s":"鷹１０","l":"三鷹駅〜武蔵野（営）Ｍ","t":3,"c":"E60013","tc":"FFFFFF","ai":"ktbus:8011201001183"},{"i":"ktbus:10106","s":"鷹１１","l":"三鷹駅〜八幡町（午後Ｂ","t":3,"c":"000000","tc":"FFFFFF","ai":"ktbus:8011201001183"},{"i":"ktbus:10107","s":"鷹１３","l":"三鷹駅〜柳沢駅","t":3,"c":"000000","tc":"FFFFFF","ai":"ktbus:8011201001183"},{"i":"ktbus:10108","s":"鷹１５","l":"三鷹駅〜東伏見駅北口","t":3,"c":"000000","tc":"FFFFFF","ai":"ktbus:8011201001183"},{"i":"ktbus:10109","s":"鷹２１","l":"三鷹駅〜天神山","t":3,"c":"000000","tc":"FFFFFF","ai":"ktbus:8011201001183"},{"i":"ktbus:10111","s":"鷹３０","l":"三鷹駅〜武蔵境駅：３０","t":3,"c":"000000","tc":"FFFFFF","ai":"ktbus:8011201001183"},{"i":"ktbus:10112","s":"鷹３３","l":"三鷹駅〜武蔵小金井駅","t":3,"c":"000000","tc":"FFFFFF","ai":"ktbus:8011201001183"},{"i":"ktbus:10113","s":"鷹３４","l":"武蔵野大〜三鷹駅：鷹３４","t":3,"c":"E60013","tc":"FFFFFF","ai":"ktbus:8011201001183"},{"i":"ktbus:10114","s":"鷹３４（直行）","l":"三鷹駅〜武蔵野大：鷹３４","t":3,"c":"E60013","tc":"FFFFFF","ai":"ktbus:8011201001183"},{"i":"ktbus:10115","s":"鷹３６","l":"関前西公園〜三鷹駅（柳）：学無","t":3,"c":"E60013","tc":"FFFFFF","ai":"ktbus:8011201001183"},{"i":"ktbus:10116","s":"鷹３７","l":"武蔵野大学〜三鷹駅：柳橋","t":3,"c":"E60013","tc":"FFFFFF","ai":"ktbus:8011201001183"},{"i":"ktbus:10117","s":"鷹４０","l":"三鷹駅〜ＮＴＴ","t":3,"c":"000000","tc":"FFFFFF","ai":"ktbus:8011201001183"},{"i":"ktbus:10118","s":"鷹４０（直行）","l":"三鷹駅〜ＮＴＴ（急行）","t":3,"c":"E60013","tc":"FFFFFF","ai":"ktbus:8011201001183"},{"i":"ktbus:10119","s":"Ｋ０１","l":"八成小〜中野駅（なかのん","t":3,"c":"E60013","tc":"FFFFFF","ai":"ktbus:8011201001183"},{"i":"ktbus:10120","s":"Ｋ０２","l":"中野駅〜八成小なかのん井","t":3,"c":"E60013","tc":"FFFFFF","ai":"ktbus:8011201001183"},{"i":"ktbus:20000","s":"","l":"わかさぎ高円寺駅","t":3,"c":"E60013","tc":"FFFFFF","ai":"ktbus:8011201001183"},{"i":"ktbus:20002","s":"","l":"シャレール荻窪〜五日市営","t":3,"c":"E60013","tc":"FFFFFF","ai":"ktbus:8011201001183"},{"i":"ktbus:20003","s":"","l":"ムーバス６号（帰り）","t":3,"c":"F27000","tc":"FFFFFF","ai":"ktbus:8011201001183"},{"i":"ktbus:20004","s":"","l":"ヴィ〜武蔵野営","t":3,"c":"E60013","tc":"FFFFFF","ai":"ktbus:8011201001183"},{"i":"ktbus:20005","s":"","l":"ヴィ〜武蔵野営（Ｈ）","t":3,"c":"E60013","tc":"FFFFFF","ai":"ktbus:8011201001183"},{"i":"ktbus:20006","s":"","l":"ヴィ〜武蔵野営（Ｈ／深）","t":3,"c":"E60013","tc":"FFFFFF","ai":"ktbus:8011201001183"},{"i":"ktbus:20007","s":"","l":"ヴィ〜武蔵野営（Ｋ）","t":3,"c":"E60013","tc":"FFFFFF","ai":"ktbus:8011201001183"},{"i":"ktbus:20008","s":"","l":"上石神井駅〜青梅（営）Ｊ","t":3,"c":"E60013","tc":"FFFFFF","ai":"ktbus:8011201001183"},{"i":"ktbus:20009","s":"","l":"上石神井駅〜青梅（営）Ｋ","t":3,"c":"E60013","tc":"FFFFFF","ai":"ktbus:8011201001183"},{"i":"ktbus:20010","s":"","l":"上石神井駅〜青梅（営）Ｋ（深）","t":3,"c":"E60013","tc":"FFFFFF","ai":"ktbus:8011201001183"},{"i":"ktbus:20011","s":"","l":"下井草駅〜営業所（深）","t":3,"c":"E60013","tc":"FFFFFF","ai":"ktbus:8011201001183"},{"i":"ktbus:20012","s":"","l":"下井草駅〜阿佐谷営業所","t":3,"c":"E60013","tc":"FFFFFF","ai":"ktbus:8011201001183"},{"i":"ktbus:20013","s":"","l":"下井草駅〜青梅街道営業所","t":3,"c":"E60013","tc":"FFFFFF","ai":"ktbus:8011201001183"},{"i":"ktbus:20014","s":"","l":"下井草駅〜青梅（営）：深","t":3,"c":"E60013","tc":"FFFFFF","ai":"ktbus:8011201001183"},{"i":"ktbus:20015","s":"","l":"中村橋〜阿佐谷営業所：Ａ","t":3,"c":"E60013","tc":"FFFFFF","ai":"ktbus:8011201001183"},{"i":"ktbus:20016","s":"","l":"中村橋〜阿佐谷営業所：Ｎ","t":3,"c":"E60013","tc":"FFFFFF","ai":"ktbus:8011201001183"},{"i":"ktbus:20017","s":"","l":"中村橋〜阿佐谷営：Ａ深","t":3,"c":"E60013","tc":"FFFFFF","ai":"ktbus:8011201001183"},{"i":"ktbus:20018","s":"","l":"中野駅〜阿佐谷営業所　中練","t":3,"c":"E60013","tc":"FFFFFF","ai":"ktbus:8011201001183"},{"i":"ktbus:20019","s":"","l":"中野駅〜阿佐谷営業所Ｎ","t":3,"c":"E60013","tc":"FFFFFF","ai":"ktbus:8011201001183"},{"i":"ktbus:20020","s":"","l":"中野駅〜阿佐谷営業所Ｓ","t":3,"c":"E60013","tc":"FFFFFF","ai":"ktbus:8011201001183"},{"i":"ktbus:20021","s":"","l":"丸山〜学田橋〜中村橋","t":3,"c":"E60013","tc":"FFFFFF","ai":"ktbus:8011201001183"},{"i":"ktbus:20022","s":"","l":"丸山〜江古田の森（セ）","t":3,"c":"E60013","tc":"FFFFFF","ai":"ktbus:8011201001183"},{"i":"ktbus:20023","s":"","l":"丸山営業所〜江古田駅","t":3,"c":"E60013","tc":"FFFFFF","ai":"ktbus:8011201001183"},{"i":"ktbus:20025","s":"","l":"丸山営業所〜練馬駅","t":3,"c":"E60013","tc":"FFFFFF","ai":"ktbus:8011201001183"},{"i":"ktbus:20026","s":"","l":"丸山（営）〜江古田の森","t":3,"c":"E60013","tc":"FFFFFF","ai":"ktbus:8011201001183"},{"i":"ktbus:20027","s":"","l":"久我山病院〜五日市（営）","t":3,"c":"E60013","tc":"FFFFFF","ai":"ktbus:8011201001183"},{"i":"ktbus:20028","s":"","l":"五日市営〜シャレール荻窪","t":3,"c":"E60013","tc":"FFFFFF","ai":"ktbus:8011201001183"},{"i":"ktbus:20029","s":"","l":"五日市街道入庫（回送）","t":3,"c":"E60013","tc":"FFFFFF","ai":"ktbus:8011201001183"},{"i":"ktbus:20030","s":"","l":"五日市（営）〜久我山病院","t":3,"c":"E60013","tc":"FFFFFF","ai":"ktbus:8011201001183"},{"i":"ktbus:20031","s":"","l":"五日市（営）〜北野","t":3,"c":"E60013","tc":"FFFFFF","ai":"ktbus:8011201001183"},{"i":"ktbus:20032","s":"","l":"五日市（営）〜宮前３丁目","t":3,"c":"E60013","tc":"FFFFFF","ai":"ktbus:8011201001183"},{"i":"ktbus:20033","s":"","l":"五日市（営）〜年金機構","t":3,"c":"E60013","tc":"FFFFFF","ai":"ktbus:8011201001183"},{"i":"ktbus:20034","s":"","l":"五日市（営）〜芦花公園駅","t":3,"c":"E60013","tc":"FFFFFF","ai":"ktbus:8011201001183"},{"i":"ktbus:20035","s":"","l":"井荻駅〜青梅街道営業所Ｉ","t":3,"c":"E60013","tc":"FFFFFF","ai":"ktbus:8011201001183"},{"i":"ktbus:20036","s":"","l":"井荻駅〜青梅街道営業所Ｎ","t":3,"c":"E60013","tc":"FFFFFF","ai":"ktbus:8011201001183"},{"i":"ktbus:20037","s":"","l":"北裏〜武蔵野（営）","t":3,"c":"E60013","tc":"FFFFFF","ai":"ktbus:8011201001183"},{"i":"ktbus:20038","s":"","l":"北裏〜武蔵野（営）：深","t":3,"c":"E60013","tc":"FFFFFF","ai":"ktbus:8011201001183"},{"i":"ktbus:20039","s":"","l":"北裏〜青梅街道（営）","t":3,"c":"E60013","tc":"FFFFFF","ai":"ktbus:8011201001183"},{"i":"ktbus:20040","s":"","l":"北裏〜青梅街道（営）（深）","t":3,"c":"E60013","tc":"FFFFFF","ai":"ktbus:8011201001183"},{"i":"ktbus:20041","s":"","l":"北野〜五日市（営）","t":3,"c":"E60013","tc":"FFFFFF","ai":"ktbus:8011201001183"},{"i":"ktbus:20042","s":"","l":"南善福寺〜青梅街道（営）","t":3,"c":"E60013","tc":"FFFFFF","ai":"ktbus:8011201001183"},{"i":"ktbus:20043","s":"","l":"向台町５〜武蔵野（営）Ｈ","t":3,"c":"E60013","tc":"FFFFFF","ai":"ktbus:8011201001183"},{"i":"ktbus:20044","s":"","l":"向台５〜武蔵野（営）Ｋ","t":3,"c":"E60013","tc":"FFFFFF","ai":"ktbus:8011201001183"},{"i":"ktbus:20045","s":"","l":"向台５〜武蔵野（営）Ｋ　学","t":3,"c":"E60013","tc":"FFFFFF","ai":"ktbus:8011201001183"},{"i":"ktbus:20046","s":"","l":"宮前３丁目〜五日市（営）","t":3,"c":"E60013","tc":"FFFFFF","ai":"ktbus:8011201001183"},{"i":"ktbus:20047","s":"","l":"宮前３丁目〜五日市（深）","t":3,"c":"E60013","tc":"FFFFFF","ai":"ktbus:8011201001183"},{"i":"ktbus:20048","s":"","l":"年金機構〜五日市（営）","t":3,"c":"E60013","tc":"FFFFFF","ai":"ktbus:8011201001183"},{"i":"ktbus:20049","s":"","l":"柳沢駅〜武蔵野（営）Ｋ深","t":3,"c":"E60013","tc":"FFFFFF","ai":"ktbus:8011201001183"},{"i":"ktbus:20050","s":"","l":"柳沢駅前〜武蔵野（営）Ｈ","t":3,"c":"000000","tc":"FFFFFF","ai":"ktbus:8011201001183"},{"i":"ktbus:20051","s":"","l":"柳沢駅前〜武蔵野（営）Ｋ","t":3,"c":"E60013","tc":"FFFFFF","ai":"ktbus:8011201001183"},{"i":"ktbus:20053","s":"","l":"武蔵境駅〜武蔵野（営）Ｙ","t":3,"c":"E60013","tc":"FFFFFF","ai":"ktbus:8011201001183"},{"i":"ktbus:20055","s":"","l":"武蔵野中央公園→第五小学校→三鷹駅","t":3,"c":"E60013","tc":"FFFFFF","ai":"ktbus:8011201001183"},{"i":"ktbus:20056","s":"","l":"武蔵野営〜ヴィ","t":3,"c":"E60013","tc":"FFFFFF","ai":"ktbus:8011201001183"},{"i":"ktbus:20057","s":"","l":"武蔵野営〜ヴィ（Ｈ）","t":3,"c":"E60013","tc":"FFFFFF","ai":"ktbus:8011201001183"},{"i":"ktbus:20058","s":"","l":"武蔵野営〜ヴィ（Ｋ）","t":3,"c":"E60013","tc":"FFFFFF","ai":"ktbus:8011201001183"},{"i":"ktbus:20061","s":"","l":"武蔵野大学〜武蔵野（営","t":3,"c":"E60013","tc":"FFFFFF","ai":"ktbus:8011201001183"},{"i":"ktbus:20062","s":"","l":"武蔵野市役所〜武蔵野営業所","t":3,"c":"E60013","tc":"FFFFFF","ai":"ktbus:8011201001183"},{"i":"ktbus:20063","s":"","l":"武蔵野（営）〜北裏","t":3,"c":"E60013","tc":"FFFFFF","ai":"ktbus:8011201001183"},{"i":"ktbus:20064","s":"","l":"武蔵野（営）〜向台町５Ｈ","t":3,"c":"E60013","tc":"FFFFFF","ai":"ktbus:8011201001183"},{"i":"ktbus:20065","s":"","l":"武蔵野（営）〜向台５Ｋ","t":3,"c":"E60013","tc":"FFFFFF","ai":"ktbus:8011201001183"},{"i":"ktbus:20066","s":"","l":"武蔵野（営）〜柳沢駅Ｈ","t":3,"c":"E60013","tc":"FFFFFF","ai":"ktbus:8011201001183"},{"i":"ktbus:20067","s":"","l":"武蔵野（営）〜柳沢駅Ｋ","t":3,"c":"E60013","tc":"FFFFFF","ai":"ktbus:8011201001183"},{"i":"ktbus:20068","s":"","l":"武蔵野（営）〜武蔵境駅Ｙ　学","t":3,"c":"E60013","tc":"FFFFFF","ai":"ktbus:8011201001183"},{"i":"ktbus:20069","s":"","l":"武蔵野（営）〜武蔵関駅","t":3,"c":"E60013","tc":"FFFFFF","ai":"ktbus:8011201001183"},{"i":"ktbus:20070","s":"","l":"武蔵野（営）〜関前西公園：柳橋","t":3,"c":"E60013","tc":"FFFFFF","ai":"ktbus:8011201001183"},{"i":"ktbus:20072","s":"","l":"武蔵野（営）〜電通裏Ｋ","t":3,"c":"E60013","tc":"FFFFFF","ai":"ktbus:8011201001183"},{"i":"ktbus:20073","s":"","l":"武蔵野（営）〜ＮＴＴ","t":3,"c":"E60013","tc":"FFFFFF","ai":"ktbus:8011201001183"},{"i":"ktbus:20074","s":"","l":"武蔵関駅〜青梅街道（営）","t":3,"c":"E60013","tc":"FFFFFF","ai":"ktbus:8011201001183"},{"i":"ktbus:20075","s":"","l":"江古田の森〜丸山（営）","t":3,"c":"E60013","tc":"FFFFFF","ai":"ktbus:8011201001183"},{"i":"ktbus:20077","s":"","l":"江古田駅〜丸山営業所","t":3,"c":"E60013","tc":"FFFFFF","ai":"ktbus:8011201001183"},{"i":"ktbus:20079","s":"","l":"江古田駅〜丸山営業所：深","t":3,"c":"E60013","tc":"FFFFFF","ai":"ktbus:8011201001183"},{"i":"ktbus:20081","s":"","l":"白鷺１〜阿佐谷営業所Ａ","t":3,"c":"E60013","tc":"FFFFFF","ai":"ktbus:8011201001183"},{"i":"ktbus:20082","s":"","l":"石神井公園駅〜阿佐谷（営","t":3,"c":"7A90FF","tc":"FFFFFF","ai":"ktbus:8011201001183"},{"i":"ktbus:20083","s":"","l":"石神井公園（井荻止まり）","t":3,"c":"E60013","tc":"FFFFFF","ai":"ktbus:8011201001183"},{"i":"ktbus:20084","s":"","l":"緑町２〜車庫：１１‐２","t":3,"c":"E60013","tc":"FFFFFF","ai":"ktbus:8011201001183"},{"i":"ktbus:20085","s":"","l":"練馬駅〜丸山営業所","t":3,"c":"E60013","tc":"FFFFFF","ai":"ktbus:8011201001183"},{"i":"ktbus:20086","s":"","l":"練馬駅〜阿佐谷営業所","t":3,"c":"E60013","tc":"FFFFFF","ai":"ktbus:8011201001183"},{"i":"ktbus:20087","s":"","l":"芦花公園駅〜五日市（営）","t":3,"c":"E60013","tc":"FFFFFF","ai":"ktbus:8011201001183"},{"i":"ktbus:20088","s":"","l":"花小金井駅南口〜車庫","t":3,"c":"E60013","tc":"FFFFFF","ai":"ktbus:8011201001183"},{"i":"ktbus:20089","s":"","l":"西荻窪駅〜青梅（営）：今","t":3,"c":"E60013","tc":"FFFFFF","ai":"ktbus:8011201001183"},{"i":"ktbus:20090","s":"","l":"西荻窪駅〜青梅（営）Ｎ桃","t":3,"c":"E60013","tc":"FFFFFF","ai":"ktbus:8011201001183"},{"i":"ktbus:20091","s":"","l":"西荻窪駅〜青梅（営）Ｒ桃","t":3,"c":"E60013","tc":"FFFFFF","ai":"ktbus:8011201001183"},{"i":"ktbus:20095","s":"","l":"迂回　花小金井〜田無","t":3,"c":"E60013","tc":"FFFFFF","ai":"ktbus:8011201001183"},{"i":"ktbus:20096","s":"","l":"野方〜阿佐谷営業所","t":3,"c":"E60013","tc":"FFFFFF","ai":"ktbus:8011201001183"},{"i":"ktbus:20097","s":"","l":"野方〜（環七）〜阿佐谷営業所（深）","t":3,"c":"E60013","tc":"FFFFFF","ai":"ktbus:8011201001183"},{"i":"ktbus:20100","s":"","l":"関前西公園〜武蔵野（営）　深","t":3,"c":"E60013","tc":"FFFFFF","ai":"ktbus:8011201001183"},{"i":"ktbus:20101","s":"","l":"関前西公園〜車庫：学無","t":3,"c":"E60013","tc":"FFFFFF","ai":"ktbus:8011201001183"},{"i":"ktbus:20102","s":"","l":"阿佐谷営業所〜下井草駅","t":3,"c":"E60013","tc":"FFFFFF","ai":"ktbus:8011201001183"},{"i":"ktbus:20103","s":"","l":"阿佐谷営業所〜中村橋：Ａ","t":3,"c":"E60013","tc":"FFFFFF","ai":"ktbus:8011201001183"},{"i":"ktbus:20104","s":"","l":"阿佐谷営業所〜中村橋：Ｎ","t":3,"c":"E60013","tc":"FFFFFF","ai":"ktbus:8011201001183"},{"i":"ktbus:20105","s":"","l":"阿佐谷営業所〜中野駅　中練","t":3,"c":"E60013","tc":"FFFFFF","ai":"ktbus:8011201001183"},{"i":"ktbus:20106","s":"","l":"阿佐谷営業所〜中野駅　朝　中練","t":3,"c":"E60013","tc":"FFFFFF","ai":"ktbus:8011201001183"},{"i":"ktbus:20107","s":"","l":"阿佐谷営業所〜中野駅Ｎ","t":3,"c":"E60013","tc":"FFFFFF","ai":"ktbus:8011201001183"},{"i":"ktbus:20108","s":"","l":"阿佐谷営業所〜中野駅Ｓ","t":3,"c":"E60013","tc":"FFFFFF","ai":"ktbus:8011201001183"},{"i":"ktbus:20110","s":"","l":"阿佐谷営業所〜白鷺１Ａ","t":3,"c":"E60013","tc":"FFFFFF","ai":"ktbus:8011201001183"},{"i":"ktbus:20111","s":"","l":"阿佐谷営業所〜練馬駅","t":3,"c":"E60013","tc":"FFFFFF","ai":"ktbus:8011201001183"},{"i":"ktbus:20112","s":"","l":"阿佐谷営業所〜練馬駅：下","t":3,"c":"E60013","tc":"FFFFFF","ai":"ktbus:8011201001183"},{"i":"ktbus:20113","s":"","l":"阿佐谷営業所〜野方","t":3,"c":"E60013","tc":"FFFFFF","ai":"ktbus:8011201001183"},{"i":"ktbus:20114","s":"","l":"阿佐谷営業所〜野方：Ｂ","t":3,"c":"E60013","tc":"FFFFFF","ai":"ktbus:8011201001183"},{"i":"ktbus:20115","s":"","l":"阿佐谷営業所〜高円寺駅","t":3,"c":"E60013","tc":"FFFFFF","ai":"ktbus:8011201001183"},{"i":"ktbus:20116","s":"","l":"阿佐谷駅〜阿佐谷営Ａ深","t":3,"c":"E60013","tc":"FFFFFF","ai":"ktbus:8011201001183"},{"i":"ktbus:20117","s":"","l":"阿佐谷駅〜阿佐谷（営）新","t":3,"c":"E60013","tc":"FFFFFF","ai":"ktbus:8011201001183"},{"i":"ktbus:20118","s":"","l":"阿佐谷駅〜阿佐谷（営）石","t":3,"c":"E60013","tc":"FFFFFF","ai":"ktbus:8011201001183"},{"i":"ktbus:20119","s":"","l":"阿佐谷駅〜阿佐谷（営）Ａ","t":3,"c":"E60013","tc":"FFFFFF","ai":"ktbus:8011201001183"},{"i":"ktbus:20120","s":"","l":"阿佐谷（営〜石神井公園駅","t":3,"c":"E60013","tc":"FFFFFF","ai":"ktbus:8011201001183"},{"i":"ktbus:20121","s":"","l":"阿佐谷（営）〜阿佐谷駅新","t":3,"c":"E60013","tc":"FFFFFF","ai":"ktbus:8011201001183"},{"i":"ktbus:20122","s":"","l":"阿佐谷（営）〜阿佐谷駅石","t":3,"c":"E60013","tc":"FFFFFF","ai":"ktbus:8011201001183"},{"i":"ktbus:20123","s":"","l":"阿佐谷（営）〜阿佐谷駅Ａ","t":3,"c":"E60013","tc":"FFFFFF","ai":"ktbus:8011201001183"},{"i":"ktbus:20126","s":"","l":"青梅街道営業所〜下井草駅","t":3,"c":"E60013","tc":"FFFFFF","ai":"ktbus:8011201001183"},{"i":"ktbus:20127","s":"","l":"青梅街道営業所〜井荻駅Ｉ","t":3,"c":"E60013","tc":"FFFFFF","ai":"ktbus:8011201001183"},{"i":"ktbus:20128","s":"","l":"青梅街道営業所〜井荻駅Ｎ","t":3,"c":"E60013","tc":"FFFFFF","ai":"ktbus:8011201001183"},{"i":"ktbus:20129","s":"","l":"青梅街道（営）〜北裏","t":3,"c":"E60013","tc":"FFFFFF","ai":"ktbus:8011201001183"},{"i":"ktbus:20130","s":"","l":"青梅街道（営）〜南善福寺","t":3,"c":"E60013","tc":"FFFFFF","ai":"ktbus:8011201001183"},{"i":"ktbus:20131","s":"","l":"青梅街道（営）〜武蔵関駅","t":3,"c":"E60013","tc":"FFFFFF","ai":"ktbus:8011201001183"},{"i":"ktbus:20132","s":"","l":"青梅街道（営）〜電通裏","t":3,"c":"E60013","tc":"FFFFFF","ai":"ktbus:8011201001183"},{"i":"ktbus:20133","s":"","l":"青梅（営）〜南善福寺・朝","t":3,"c":"E60013","tc":"FFFFFF","ai":"ktbus:8011201001183"},{"i":"ktbus:20134","s":"","l":"青梅（営）〜西荻窪駅：今","t":3,"c":"E60013","tc":"FFFFFF","ai":"ktbus:8011201001183"},{"i":"ktbus:20135","s":"","l":"青梅（営）〜西荻窪駅Ｎ桃","t":3,"c":"E60013","tc":"FFFFFF","ai":"ktbus:8011201001183"},{"i":"ktbus:20136","s":"","l":"青梅（営）〜西荻窪駅Ｒ桃","t":3,"c":"E60013","tc":"FFFFFF","ai":"ktbus:8011201001183"},{"i":"ktbus:20137","s":"","l":"青（営）〜西荻Ｒ桃・折返","t":3,"c":"E60013","tc":"FFFFFF","ai":"ktbus:8011201001183"},{"i":"ktbus:20138","s":"","l":"高円寺わかさぎ","t":3,"c":"E60013","tc":"FFFFFF","ai":"ktbus:8011201001183"},{"i":"ktbus:20139","s":"","l":"高円寺駅〜阿佐谷営業所","t":3,"c":"E60013","tc":"FFFFFF","ai":"ktbus:8011201001183"},{"i":"ktbus:20140","s":"","l":"４１：江古田駅深夜前","t":3,"c":"E60013","tc":"FFFFFF","ai":"ktbus:8011201001183"},{"i":"ktbus:20141","s":"","l":"ＮＩ六都〜田無駅　北","t":3,"c":"E60013","tc":"FFFFFF","ai":"ktbus:8011201001183"},{"i":"ktbus:20143","s":"","l":"ＮＩ田無駅〜六都　西原４経由","t":3,"c":"E60013","tc":"FFFFFF","ai":"ktbus:8011201001183"},{"i":"ktbus:20144","s":"","l":"ＮＩ田無駅〜六都科学館〜花小金井駅","t":3,"c":"E60013","tc":"FFFFFF","ai":"ktbus:8011201001183"},{"i":"ktbus:20145","s":"","l":"ＮＩ田無駅〜芝久保運動場","t":3,"c":"E60013","tc":"FFFFFF","ai":"ktbus:8011201001183"},{"i":"ktbus:20146","s":"","l":"ＮＩ田無駅〜花小金井駅","t":3,"c":"E60013","tc":"FFFFFF","ai":"ktbus:8011201001183"},{"i":"ktbus:20147","s":"","l":"ＮＩ芝久保運動場〜田無駅","t":3,"c":"E60013","tc":"FFFFFF","ai":"ktbus:8011201001183"},{"i":"ktbus:20148","s":"","l":"ＮＩ花小金井駅〜田無駅","t":3,"c":"E60013","tc":"FFFFFF","ai":"ktbus:8011201001183"}]