{"bundle_version":3,"kind":"insights","serviceGroups":{"v":1,"data":[{"key":"all","serviceIds":["oksrif:20260101-0331江差","oksrif:20260401-0424江差","oksrif:20260425-0506江差","oksrif:20260507-0630江差","oksrif:20260701-0831江差","oksrif:20260901-0904江差","oksrif:20260905-0906江差","oksrif:20260907-0911江差","oksrif:20260912-0913江差","oksrif:20260914-0918江差","oksrif:20260919-0923江差","oksrif:20260924-1130江差","oksrif:20261201-1231江差"]}]},"tripPatternGeo":{"v":1,"data":{"oksrif:p1":{"dist":60.502,"pathDist":60.502,"cl":false},"oksrif:p2":{"dist":60.502,"pathDist":60.502,"cl":false}}},"tripPatternStats":{"v":1,"data":{"all":{"oksrif:p1":{"freq":18,"rd":[130,0]},"oksrif:p2":{"freq":18,"rd":[130,0]}}}},"stopStats":{"v":1,"data":{"all":{"oksrif:[01]江差港フェリーターミナル":{"freq":36,"rc":1,"rtc":1,"ed":550,"ld":1060},"oksrif:[02]奥尻港フェリーターミナル":{"freq":36,"rc":1,"rtc":1,"ed":420,"ld":1190}}}}}